online_stats.py
online_stats-2023.6.dist-info/LICENSE
online_stats-2023.6.dist-info/WHEEL
online_stats-2023.6.dist-info/METADATA
online_stats-2023.6.dist-info/RECORD
