Metadata-Version: 2.1
Name: online-stats
Version: 2023.6
Summary: Online algorithm for mean, variance, and covariance.
Keywords: online algorithm,online mean,online variance,online covariance,online statistics
Author-email: Nicolas Tessore <n.tessore@ucl.ac.uk>
Requires-Python: >=3.6
Classifier: License :: OSI Approved :: MIT License
Project-URL: Home, https://github.com/ntessore/online-stats
Project-URL: Issues, https://github.com/ntessore/online-stats/issues
